Easytexts/Easytexts.py
Easytexts/__init__.py
Easytexts-1.1.0.dist-info/LICENSE.txt
Easytexts-1.1.0.dist-info/METADATA
Easytexts-1.1.0.dist-info/WHEEL
Easytexts-1.1.0.dist-info/top_level.txt
Easytexts-1.1.0.dist-info/RECORD
