Metadata-Version: 2.1
Name: Easytexts
Version: 1.1.0
Summary: Easytexts: Simplified text management for quick and simple projects
Home-page: https://github.com/Katzover/Easytexts
Author: Itamar Katzover
Author-email: itamar43.katzover43@gmail.com
Classifier: Development Status :: 4 - Beta
Classifier: Programming Language :: Python :: 3
Classifier: License :: OSI Approved :: MIT License
Requires-Python: >=3.10
License-File: LICENSE.txt
